django_river_ml/__init__.py
django_river_ml/announce.py
django_river_ml/apps.py
django_river_ml/auth.py
django_river_ml/client.py
django_river_ml/exceptions.py
django_river_ml/flavors.py
django_river_ml/middleware.py
django_river_ml/model.py
django_river_ml/namer.py
django_river_ml/settings.py
django_river_ml/signals.py
django_river_ml/storage.py
django_river_ml/urls.py
django_river_ml/utils.py
django_river_ml/version.py
django_river_ml/management/commands/__init__.py
django_river_ml/management/commands/get_token.py
django_river_ml/views/__init__.py
django_river_ml/views/auth.py
django_river_ml/views/base.py
django_river_ml/views/label.py
django_river_ml/views/learn.py
django_river_ml/views/metrics.py
django_river_ml/views/model.py
django_river_ml/views/predict.py
django_river_ml-0.0.21.dist-info/AUTHORS.md
django_river_ml-0.0.21.dist-info/LICENSE
django_river_ml-0.0.21.dist-info/METADATA
django_river_ml-0.0.21.dist-info/WHEEL
django_river_ml-0.0.21.dist-info/top_level.txt
django_river_ml-0.0.21.dist-info/RECORD
