Metadata-Version: 2.1
Name: django-river-ml
Version: 0.0.21
Summary: Online machine learning with river and Django.
Home-page: https://github.com/vsoch/django-river-ml
Author: Vanessa Sochat
Author-email: vsoch@users.noreply.github.io
License: Apache Software License 2.0
Keywords: online-ml,river,chantilly
Classifier: Development Status :: 3 - Alpha
Classifier: Framework :: Django :: 1.11
Classifier: Framework :: Django :: 2.1
Classifier: Intended Audience :: Developers
Classifier: License :: OSI Approved :: BSD License
Classifier: Natural Language :: English
Classifier: Programming Language :: Python :: 3.7
License-File: LICENSE
License-File: AUTHORS.md
Requires-Dist: django
Requires-Dist: djangorestframework
Requires-Dist: django-ratelimit
Requires-Dist: pyjwt
Requires-Dist: river
Requires-Dist: redis
Requires-Dist: dill
Requires-Dist: cerebrus
